rest_bootstraptable_pagination/pagination.py
rest_bootstraptable_pagination/__init__.py
rest_bootstraptable_pagination-1.0.1.dist-info/DESCRIPTION.rst
rest_bootstraptable_pagination-1.0.1.dist-info/METADATA
rest_bootstraptable_pagination-1.0.1.dist-info/metadata.json
rest_bootstraptable_pagination-1.0.1.dist-info/top_level.txt
rest_bootstraptable_pagination-1.0.1.dist-info/WHEEL
rest_bootstraptable_pagination-1.0.1.dist-info/RECORD
