Metadata-Version: 2.0
Name: rest-bootstraptable-pagination
Version: 1.0.1
Summary: Django RestFramework pagination For bootstrap-table.
Home-page: https://github.com/songhuagao/rest-bootstraptable-pagination
Author: Justin Chen
Author-email: songhuagao@gmail.com
License: MIT
Platform: any
Requires-Dist: django
Requires-Dist: djangorestframework
